reranker/__init__.py
reranker/distance.py
reranker/ranker.py
reranker/spec.py
reranker-0.2.3.dist-info/LICENSE
reranker-0.2.3.dist-info/METADATA
reranker-0.2.3.dist-info/WHEEL
reranker-0.2.3.dist-info/top_level.txt
reranker-0.2.3.dist-info/RECORD
