Metadata-Version: 2.1
Name: reranker
Version: 0.2.3
Summary: Argument parsing with structured class.
Author-email: Keming <kemingy94@gmail.com>
License: Apache-2.0
Project-URL: Homepage, https://github.com/kemingy/reranker
Classifier: Intended Audience :: Developers
Requires-Python: >=3.8
License-File: LICENSE
Requires-Dist: msgspec
Requires-Dist: httpx
Requires-Dist: cohere
Requires-Dist: numpy
Requires-Dist: typing-extensions
Provides-Extra: dev
Requires-Dist: ruff ~=0.2.0 ; extra == 'dev'
Requires-Dist: pytest ~=7.4 ; extra == 'dev'
